geoclone/__init__.py
geoclone/common.py
geoclone/geoclone.py
geoclone-0.0.2.dist-info/LICENSE
geoclone-0.0.2.dist-info/METADATA
geoclone-0.0.2.dist-info/WHEEL
geoclone-0.0.2.dist-info/entry_points.txt
geoclone-0.0.2.dist-info/top_level.txt
geoclone-0.0.2.dist-info/RECORD
